argil/__init__.py
argil/api_definitions.py
argil/argil_config.py
argil/argil_error.py
argil-0.0.6.dist-info/LICENCE.md
argil-0.0.6.dist-info/METADATA
argil-0.0.6.dist-info/WHEEL
argil-0.0.6.dist-info/top_level.txt
argil-0.0.6.dist-info/RECORD
